README.md
setup.py
ubuntu_release_names/__init__.py
ubuntu_release_names/main.py
ubuntu_release_names.egg-info/PKG-INFO
ubuntu_release_names.egg-info/SOURCES.txt
ubuntu_release_names.egg-info/dependency_links.txt
ubuntu_release_names.egg-info/entry_points.txt
ubuntu_release_names.egg-info/requires.txt
ubuntu_release_names.egg-info/top_level.txt