Metadata-Version: 2.1
Name: ubuntu-release-names
Version: 1.0.0
Summary: Fetch the current ubuntu release names and versions from wikipedia
Home-page: 
Author: @readwithai
Author-email: talwrii@gmail.com
License: GPLv3
Keywords: ubuntu,release,versios
Requires-Dist: lxml
